greater_tables/__init__.py
greater_tables/cli.py
greater_tables/config.py
greater_tables/core.py
greater_tables/enums.py
greater_tables/etcher.py
greater_tables/fabrications.py
greater_tables/formats.py
greater_tables/gtlogging.py
greater_tables/hasher.py
greater_tables/utilities.py
greater_tables/data/__init__.py
greater_tables/data/blog.csv
greater_tables/data/book.csv
greater_tables/data/notes.csv
greater_tables/data/tex_list.csv
greater_tables/data/tex_list.py
greater_tables/data/words-12.md
greater_tables-5.2.1.dist-info/licenses/LICENSE
greater_tables-5.2.1.dist-info/METADATA
greater_tables-5.2.1.dist-info/WHEEL
greater_tables-5.2.1.dist-info/entry_points.txt
greater_tables-5.2.1.dist-info/top_level.txt
greater_tables-5.2.1.dist-info/RECORD
