Metadata-Version: 2.4
Name: greater_tables
Version: 5.2.1
Summary: Perfect tables from pandas dataframes.
Author-email: Stephen J Mildehall <mynl@me.com>
License-Expression: MIT
Project-URL: Source Code, https://github.com/mynl/greater_tables_project
Project-URL: Documentation, https://greater-tables-project.readthedocs.io/en/latest/
Project-URL: Changelog, https://greater-tables-project.readthedocs.io/en/latest/versions.html
Classifier: Development Status :: 4 - Beta
Classifier: Programming Language :: Python :: 3
Classifier: Programming Language :: Python :: 3.10
Classifier: Programming Language :: Python :: 3.11
Classifier: Programming Language :: Python :: 3.12
Classifier: Topic :: Office/Business
Requires-Python: >=3.10
License-File: LICENSE
Requires-Dist: beautifulsoup4
Requires-Dist: cachetools
Requires-Dist: pydantic
Requires-Dist: click
Requires-Dist: pandas
Requires-Dist: rich
Requires-Dist: IPython
Provides-Extra: dev
Requires-Dist: docutils<0.17; extra == "dev"
Requires-Dist: jupyter-sphinx; extra == "dev"
Requires-Dist: myst_parser; extra == "dev"
Requires-Dist: nbsphinx; extra == "dev"
Requires-Dist: pickleshare; extra == "dev"
Requires-Dist: recommonmark>=0.7.1; extra == "dev"
Requires-Dist: setuptools>=62.3.2; extra == "dev"
Requires-Dist: sphinx>=5.0; extra == "dev"
Requires-Dist: sphinx-panels; extra == "dev"
Requires-Dist: sphinx-rtd-dark-mode; extra == "dev"
Requires-Dist: sphinxcontrib-bibtex; extra == "dev"
Requires-Dist: sphinx-copybutton; extra == "dev"
Requires-Dist: sphinx-toggleprompt; extra == "dev"
Requires-Dist: sphinx-multitoc-numbering; extra == "dev"
Dynamic: license-file
